trans007/__init__.py
trans007/google.py
trans007-0.1.2.dist-info/LICENSE
trans007-0.1.2.dist-info/METADATA
trans007-0.1.2.dist-info/WHEEL
trans007-0.1.2.dist-info/top_level.txt
trans007-0.1.2.dist-info/RECORD
